{
	"users":
	[  
		{
			"id"     : "francois-leproust",
			"name"   : "François Leproust",
			"desc"   : "",
			"avatar" : "francois-leproust",
			"job"    : "webdesigner & developpeur front-end",
			"email"  : "hello@mr-rayures.com",
			"website": "https://mr-rayures.com/"
		},
		{
			"id"     : "nicolas-glorieux",
			"name"   : "Nicolas Glorieux",
			"desc"   : "",
			"avatar" : "nicolas-glorieux",
			"job"    : "réalisateur de documentaire",
			"email"  : "nicolas.t.glorieux@gmail.com",
			"website": "http://nicolasglorieux.wix.com/video"
		},
		{
			"id"     : "olivier-thomas",
			"name"   : "Olivier Thomas",
			"desc"   : "",
			"avatar" : "olivier-thomas",
			"job"    : "dessinateur BD",
			"email"  : "olivezthomas@gmail.com",
			"website": "https://www.instagram.com/olivier29thomas/"
		},
		{
			"id"     : "angele-villeneuve",
			"name"   : "Angèle Villeneuve",
			"desc"   : "",
			"avatar" : "angele-villeneuve",
			"job"    : "Dessinatrice : illustrations et créations graphiques",
			"email"  : "angele.newtown@gmail.com",
			"website": "https://angelevilleneuve.wixsite.com/angelevilleneuve"
		},
		{
			"id"     : "laurent-bourlaud",
			"name"   : "Laurent Bourlaud",
			"desc"   : "",
			"avatar" : "laurent-bourlaud",
			"job"    : "auteur, illustrateur, graphiste",
			"email"  : "laurent.bourlaud@gmail.com",
			"website": "http://laurentbourlaud.tumblr.com/"
		},
		{
			"id"   : "miss-paty",
			"name"   : "MissPATY",
			"desc"   : "",
			"avatar" : "miss-paty",
			"job"    : "autrice-illustratrice",
			"email"  : "little.misspaty@gmail.com",
			"website": "https://misspaty.com/",
      "insta"  : "https://www.instagram.com/misspaty/"
		},
    {
			"id"   : "giorgia-marras",
			"name"   : "Giorgia Marras",
			"desc"   : "",
			"avatar" : "placeholder",
			"job"    : "",
			"email"  : "",
			"website": ""
		},
    {
			"id"   : "giorgia-casetti",
			"name"   : "Giorgia Casetti",
			"desc"   : "",
			"avatar" : "placeholder",
			"job"    : "",
			"email"  : "",
			"website": ""
		},
    {
			"id"   : "séverine-fraud",
			"name"   : "Séverine Fraud",
			"desc"   : "",
			"avatar" : "placeholder",
			"job"    : "",
			"email"  : "",
			"website": ""
		},
    {
			"id"   : "benoit-hamet",
			"name"   : "Benoît Hamet",
			"desc"   : "",
			"avatar" : "placeholder",
			"job"    : "",
			"email"  : "",
			"website": ""
		},
    {
			"id"   : "line-pauvert",
			"name"   : "Line Pauvert",
			"desc"   : "",
			"avatar" : "placeholder",
			"job"    : "",
			"email"  : "",
			"website": ""
		}
	]
}  